{
  "author": "AFFiNE",
  "authors": [
    "AFFiNE"
  ],
  "createDate": 1727207396703,
  "created": 1727136000000,
  "description": " ",
  "guid": "vuKw8EzafqFzJ2ea1c9Le",
  "id": "vuKw8EzafqFzJ2ea1c9Le",
  "linkedPageIds": [
    "wKajtPI07JYuntehvqZQ8",
    "mhXkUvwacMxFPXrxlUQEF",
    "y3GwFuCD7PCzfmAihbd5m",
    "EzCZzdu56cBrqqDab4RtK",
    "oapgNIuMNG",
    "sCGzzgL7ehx7YswYLAozx",
    "8yoI71clK3"
  ],
  "md": "A **Weekly Planner Goal Set** is the perfect tool for organizing and prioritizing your weekly objectives, ensuring that you stay on track and make meaningful progress towards your goals. This planner allows you to break down your larger tasks into manageable steps, set clear targets for the week, and evaluate your accomplishments. Whether you’re balancing work, school, personal projects, or fitness goals, a weekly goal set planner helps you focus on what matters most. By mapping out your week ahead, you can efficiently manage your time, stay motivated, and achieve more.\n\n\n## **Key Features of the Weekly Planner Goal Set**\n\n\n### **1. Weekly Goals**\n\n\nThe **weekly goals** section helps you define the most important tasks and objectives to complete by the end of the week, giving you a clear direction to follow.\n\n\n### **2. Daily Breakdown**\n\n\nWith a **daily breakdown**, you can distribute your tasks across the week, ensuring that every day contributes to the completion of your goals while preventing overwhelm.\n\n\n### **3. Progress Tracking and Review**\n\n\nThe **progress tracking** and **weekly review** section lets you reflect on your performance, assess what worked well, and identify areas for improvement, fostering continuous growth.\n\n\n|Title|\n|---|\n|[](LinkedPage:mhXkUvwacMxFPXrxlUQEF)<br /><br /><br />|\n|[](LinkedPage:y3GwFuCD7PCzfmAihbd5m:page)<br /><br /><br />|\n|[](LinkedPage:EzCZzdu56cBrqqDab4RtK:page)<br /><br /><br />|\n\n\n",
  "publish": true,
  "relatedBlogIds": [
    "oapgNIuMNG",
    "sCGzzgL7ehx7YswYLAozx",
    "8yoI71clK3"
  ],
  "relatedBlogs": [
    "5-best-free-daily-planner-apps-for-2023",
    "free-and-printable-family-tree-templates",
    "best-open-source-notion-alternatives"
  ],
  "slug": "weekly-planner-goal-set-website",
  "tags": [
    "Digital Planner"
  ],
  "template": "LinkedPage:wKajtPI07JYuntehvqZQ8:page",
  "title": "Weekly Planner Goal Set Website",
  "updatedDate": 1727271924584,
  "valid": false
}